zmfcli/__init__.py
zmfcli/logrequests.py
zmfcli/session.py
zmfcli/zmf.py
zmfcli-0.1.19.dist-info/LICENSE
zmfcli-0.1.19.dist-info/METADATA
zmfcli-0.1.19.dist-info/WHEEL
zmfcli-0.1.19.dist-info/entry_points.txt
zmfcli-0.1.19.dist-info/top_level.txt
zmfcli-0.1.19.dist-info/zip-safe
zmfcli-0.1.19.dist-info/RECORD
